{"id":"0029-sweet-rehab-beef-yakiudon","title":"## Beef Yakiudon","img":"![](imgs/0029-yaki-udon.webp)\n\n[#url]:#()\n\n[]()","recipeTime":{"previousDay":false,"totalTime":"25","cookingTime":"10"},"ingredientsContent":"### \n2 blocks of frozen sanuki udon\n* 2 teaspoon sesame oil\n* 2 tablespoon unsalted butter\n* 1 clove garlic, crushed\n* 1 shallot, sliced *(alternatively, you can use a quarter of a small onion)*\n* 150 grams of sliced beef\n* 125 grams Mushrooms, sliced *(any type, I prefer shiitake and shimeji but couldn’t locate those in the grocery store today)*\n* 25 ml soy sauce\n* 1 tablespoon oyster sauce\n* 2 teaspoon mirin\n* 1 teaspoon Japanese Worcestershire sauce *(optional)*\n\n* 1/4 cup dashi stock\n\nGarnish suggestions:\n* Dash Shichimi Togarashi *(Japanese 7 spice)*\n* 1 Green onion stalk, sliced\n* 1 tablespoon Bonito flakes\n* Nori strips\n* Egg Yolk","content":"1. In a medium saucepan, bring to boil water on high heat.\n2. Once the water starts boiling, add the frozen udon to cook for about 2\nminutes.\n3. Strain the water well through a wire strainer and set aside.\n4. In a skillet or wok, heat the sesame oil and butter until melted on\nmedium heat.\n5. Next, add the onions and garlic. Stir and fry for about a minute.\n6. Add the sliced mushrooms and cook for about 3 minutes.\n7. Add the beef and cook until it is no longer pink.\n8. Add the udon to the skillet or wok.\n9. Add the soy sauce, oyster sauce, mirin, and Worcestershire sauce.\n10. Stir and fry everything together for about 30 seconds.\n11. Next add the dashi stock, and mix everything together. If preferred,\nadd more dashi stock or butter to loosen the noodles.\n12. After stir-frying for a minute the dish is complete.\n13. Plate the noodles and top with your preferred garnishes. *I like to\nplate mine with all the garnishes, since I have*"}
